ephemeraldb/__init__.py
ephemeraldb/core.py
ephemeraldb/exceptions.py
ephemeraldb-1.0.0.dist-info/licenses/LICENSE
examples/01_basic_usage.py
examples/02_scope_management.py
examples/03_context_manager.py
examples/04_dsl_interpreter.py
examples/05_configuration_parser.py
examples/06_template_engine.py
examples/07_state_machine.py
examples/08_transaction_system.py
examples/09_debugging_context.py
examples/10_cache_system.py
examples/__init__.py
tests/__init__.py
tests/conftest.py
tests/test_core.py
tests/test_examples.py
ephemeraldb-1.0.0.dist-info/METADATA
ephemeraldb-1.0.0.dist-info/WHEEL
ephemeraldb-1.0.0.dist-info/top_level.txt
ephemeraldb-1.0.0.dist-info/RECORD
